pysegy/__init__.py
pysegy/ibm.py
pysegy/plotting.py
pysegy/read.py
pysegy/scan.py
pysegy/types.py
pysegy/utils.py
pysegy/write.py
pysegy/tests/test_async.py
pysegy/tests/test_extra.py
pysegy/tests/test_python.py
pysegy-0.4.0.dist-info/licenses/LICENSE
pysegy-0.4.0.dist-info/METADATA
pysegy-0.4.0.dist-info/WHEEL
pysegy-0.4.0.dist-info/top_level.txt
pysegy-0.4.0.dist-info/RECORD
