Metadata-Version: 2.4
Name: pysegy
Version: 0.4.0
Summary: Minimal Python implementation of SegyIO
Author-email: Mathias Louboutin <mathias@devitocodes.com>
License: MIT License
Classifier: Programming Language :: Python :: 3
Requires-Python: >=3.10
License-File: LICENSE
Requires-Dist: numpy<3,>=2
Requires-Dist: fsspec>=2024.3
Requires-Dist: cloudpickle>=3
Requires-Dist: matplotlib>=3.7
Provides-Extra: dev
Requires-Dist: flake8; extra == "dev"
Requires-Dist: flake8-pyproject; extra == "dev"
Dynamic: license-file
